Workbook

Sheet Übersicht
A1: Depot-Look-through: Einzelaktien inklusive Fonds und ETFs
A2: Depotwerte: 17.07.2026 | Fonds-/ETF-Bestände: 10.–16.07.2026 | Unternehmen nach offensichtlichen Aktienklassen konsolidiert
A4: Kennzahl | B4: Wert
A5: Gesamtvermögen | B5: 110400.89
A6: Direkte Einzelaktien | B6: 52033.96
A7: Indirekt aufgelöste Einzelaktien | B7: 43140.442
A8: Aufgelöste Aktienexposure gesamt | B8: 95174.402
A9: Nicht aufgelöst / keine Einzelaktien | B9: 15226.488
A10: Anzahl konsolidierter Unternehmen | B10: 1288
A12: Rang | B12: Unternehmen | C12: Sektor | D12: Direkt (€) | E12: Indirekt (€) | F12: Gesamt-Exposure (€) | G12: Anteil Gesamtvermögen | H12: Aktienfonds (€) | I12: Global Titans (€) | J12: Technologiefonds 60% (€) | K12: MSCI World (€) | L12: World Value (€)
A13: 1 | B13: Berkshire Hathaway | C13: Financials | D13: 23600.5 | E13: 578.53782 | F13: 24179.038 | G13: 0.21901126 | H13: 552.97811 | I13: 0 | J13: 0 | K13: 25.559712 | L13: 0
A14: 2 | B14: Nvidia | C14: Information Technology | D14: 4430.5 | E14: 1929.2743 | F14: 6359.7743 | G14: 0.057606187 | H14: 601.46406 | I14: 1061.7518 | J14: 86.804207 | K14: 179.2543 | L14: 0
A15: 3 | B15: Alphabet | C15: Communication | D15: 3328.6 | E15: 1801.5608 | F15: 5130.1608 | G15: 0.046468474 | H15: 555.08205 | I15: 1024.4973 | J15: 83.420928 | K15: 138.56054 | L15: 0
A16: 4 | B16: Allianz | C16: Financials | D16: 4210 | E16: 580.0219 | F16: 4790.0219 | G16: 0.04338753 | H16: 573.29566 | I16: 0 | J16: 0 | K16: 6.72624 | L16: 0
A17: 5 | B17: AMD | C17: Information Technology | D17: 3896.55 | E17: 697.78379 | F17: 4594.3338 | G17: 0.041615007 | H17: 573.30194 | I17: 0 | J17: 93.877466 | K17: 30.604392 | L17: 0
A18: 6 | B18: Microsoft | C18: Information Technology | D18: 2410.1 | E18: 1806.3823 | F18: 4216.4823 | G18: 0.038192467 | H18: 573.75232 | I18: 1036.472 | J18: 90.219784 | K18: 105.93828 | L18: 0
A19: 7 | B19: Apple | C19: Information Technology | D19: 1458.25 | E19: 2068.3081 | F19: 3526.5581 | G19: 0.031943203 | H19: 615.1246 | I19: 1173.5151 | J19: 96.714621 | K19: 182.95373 | L19: 0
A20: 8 | B20: Eli Lilly | C20: Health Care | D20: 2060.8 | E20: 933.23275 | F20: 2994.0328 | G20: 0.027119643 | H20: 536.35595 | I20: 361.90035 | J20: 0 | K20: 34.976448 | L20: 0
A21: 9 | B21: TSMC | C21: Information Technology | D21: 696 | E21: 1324.8169 | F21: 2020.8169 | G21: 0.018304353 | H21: 529.24686 | I21: 723.8007 | J21: 71.769335 | K21: 0 | L21: 0
A22: 10 | B22: Siemens | D22: 1851.5 | E22: 80.610658 | F22: 1932.1107 | G22: 0.017500861 | H22: 0 | I22: 0 | J22: 80.610658 | K22: 0 | L22: 0
A23: 11 | B23: HSBC | C23: Financials | D23: 1702.16 | E23: 160.01699 | F23: 1862.177 | G23: 0.016867409 | H23: 0 | I23: 135.71263 | J23: 0 | K23: 12.779856 | L23: 11.524504
A24: 12 | B24: Amazon | C24: Consumer Discretionary | D24: 0 | E24: 1705.6751 | F24: 1705.6751 | G24: 0.015449831 | H24: 567.84793 | I24: 959.30204 | J24: 88.057173 | K24: 90.467928 | L24: 0
A25: 13 | B25: Micron Technology | C25: Information Technology | D25: 1492.2 | E25: 186.48856 | F25: 1678.6886 | G25: 0.01520539 | H25: 0 | I25: 0 | J25: 0 | K25: 35.985384 | L25: 150.50318
A26: 14 | B26: Linde | C26: Materials | D26: 896.8 | E26: 103.54706 | F26: 1000.3471 | G26: 0.0090610416 | H26: 0 | I26: 94.466636 | J26: 0 | K26: 9.080424 | L26: 0
A27: 15 | B27: ASML | C27: Information Technology | D27: 0 | E27: 931.18791 | F27: 931.18791 | G27: 0.0084346051 | H27: 548.22921 | I27: 278.07784 | J27: 78.312211 | K27: 26.568648 | L27: 0
A28: 16 | B28: Broadcom | C28: Information Technology | D28: 0 | E28: 840.4393 | F28: 840.4393 | G28: 0.0076126135 | H28: 0 | I28: 694.52935 | J28: 83.019604 | K28: 62.890344 | L28: 0
A29: 17 | B29: Visa | C29: Financials | D29: 0 | E29: 822.22896 | F29: 822.22896 | G29: 0.007447666 | H29: 561.19738 | I29: 238.16236 | J29: 0 | K29: 22.869216 | L29: 0
A30: 18 | B30: Netflix | C30: Communication | D30: 0 | E30: 766.88359 | F30: 766.88359 | G30: 0.0069463533 | H30: 545.7117 | I30: 122.40747 | J30: 86.993496 | K30: 11.77092 | L30: 0
A31: 19 | B31: Mastercard | C31: Financials | D31: 0 | E31: 760.81545 | F31: 760.81545 | G31: 0.0068913887 | H31: 569.70225 | I31: 174.2976 | J31: 0 | K31: 16.8156 | L31: 0
A32: 20 | B32: SAP | C32: Information Technology | D32: 0 | E32: 714.6136 | F32: 714.6136 | G32: 0.0064728971 | H32: 560.15032 | I32: 62.534252 | J32: 85.875411 | K32: 6.053616 | L32: 0
A33: 21 | B33: T-Mobile US | D33: 0 | E33: 688.23899 | F33: 688.23899 | G33: 0.0062339985 | H33: 592.34453 | I33: 0 | J33: 95.894458 | K33: 0 | L33: 0
A34: 22 | B34: Caterpillar | C34: Industrials | D34: 0 | E34: 687.87404 | F34: 687.87404 | G34: 0.0062306929 | H34: 514.4086 | I34: 158.3314 | J34: 0 | K34: 15.13404 | L34: 0
A35: 23 | B35: McDonald's | C35: Consumer Discretionary | D35: 0 | E35: 647.32463 | F35: 647.32463 | G35: 0.0058634005 | H35: 564.08635 | I35: 75.839412 | J35: 0 | K35: 7.398864 | L35: 0
A36: 24 | B36: Booking Holdings | C36: Consumer Discretionary | D36: 0 | E36: 635.87322 | F36: 635.87322 | G36: 0.0057596747 | H36: 543.19522 | I36: 0 | J36: 86.960697 | K36: 5.717304 | L36: 0
A37: 25 | B37: Nasdaq Inc. | C37: Financials | D37: 0 | E37: 631.04708 | F37: 631.04708 | G37: 0.0057159601 | H37: 629.36552 | I37: 0 | J37: 0 | K37: 1.68156 | L37: 0
A39: Wichtige Abgrenzung: Beim boerse.de-Technologiefonds sind nur die öffentlich vollständig aufgeführten 60% des Basisportfolios auf Unternehmen verteilt. Das 40%-Darwin-Portfolio mit mehr als 500 Technologieaktien ist nicht vollständig öffentlich auflösbar. Die dort enthaltenen Unternehmensanteile fehlen daher in den Einzelwerten.

Sheet Alle Unternehmen
A1: Rang | B1: Unternehmen | C1: Sektor | D1: Direktbestand (€) | E1: boerse.de-Aktienfonds (€) | F1: Global Titans 50 (€) | G1: boerse.de-Technologiefonds – öffentl. 60% (€) | H1: MSCI World (€) | I1: World Value (€) | J1: Indirekt gesamt (€) | K1: Gesamt-Exposure (€) | L1: Anteil Gesamtvermögen | M1: Enthalten in | N1: Quellen
A2: 1 | B2: Berkshire Hathaway | C2: Financials | D2: 23600.5 | E2: 552.97811 | F2: 0 | G2: 0 | H2: 25.559712 | I2: 0 | J2: =SUM(E2:I2) -> 578.53782 | K2: =D2+J2 -> 24179.038 | L2: =K2/'Quellen & Annahmen'!$B$2 -> 0.21901126 | M2: Direkt; boerse.de-Aktienfonds; MSCI World | N2: Nutzerangaben im Chat; https://www.boerse-aktienfonds.de/; https://www.ishares.com/ch/individual/en/products/251882/ishares-msci-world-ucits-etf-acc-fund
A3: 2 | B3: Nvidia | C3: Information Technology | D3: 4430.5 | E3: 601.46406 | F3: 1061.7518 | G3: 86.804207 | H3: 179.2543 | I3: 0 | J3: =SUM(E3:I3) -> 1929.2743 | K3: =D3+J3 -> 6359.7743 | L3: =K3/'Quellen & Annahmen'!$B$2 -> 0.057606187 | M3: Direkt; boerse.de-Aktienfonds; Global Titans 50; boerse.de-Technologiefonds (60% offengelegt); MSCI World | N3: Nutzerangaben im Chat; https://www.boerse-aktienfonds.de/; https://www.ishares.com/ch/professionals/en/products/251769/ishares-dow-jones-global-titans-50-ucits-etf-de-fund; https://www.boerse-technologiefonds.de/; https://www.ishares.com/ch/individual/en/products/251882/ishares-msci-world-ucits-etf-acc-fund
A4: 3 | B4: Alphabet | C4: Communication | D4: 3328.6 | E4: 555.08205 | F4: 1024.4973 | G4: 83.420928 | H4: 138.56054 | I4: 0 | J4: =SUM(E4:I4) -> 1801.5608 | K4: =D4+J4 -> 5130.1608 | L4: =K4/'Quellen & Annahmen'!$B$2 -> 0.046468474 | M4: Direkt; boerse.de-Aktienfonds; Global Titans 50; boerse.de-Technologiefonds (60% offengelegt); MSCI World | N4: Nutzerangaben im Chat; https://www.boerse-aktienfonds.de/; https://www.ishares.com/ch/professionals/en/products/251769/ishares-dow-jones-global-titans-50-ucits-etf-de-fund; https://www.boerse-technologiefonds.de/; https://www.ishares.com/ch/individual/en/products/251882/ishares-msci-world-ucits-etf-acc-fund
A5: 4 | B5: Allianz | C5: Financials | D5: 4210 | E5: 573.29566 | F5: 0 | G5: 0 | H5: 6.72624 | I5: 0 | J5: =SUM(E5:I5) -> 580.0219 | K5: =D5+J5 -> 4790.0219 | L5: =K5/'Quellen & Annahmen'!$B$2 -> 0.04338753 | M5: Direkt; boerse.de-Aktienfonds; MSCI World | N5: Nutzerangaben im Chat; https://www.boerse-aktienfonds.de/; https://www.ishares.com/ch/individual/en/products/251882/ishares-msci-world-ucits-etf-acc-fund
A6: 5 | B6: AMD | C6: Information Technology | D6: 3896.55 | E6: 573.30194 | F6: 0 | G6: 93.877466 | H6: 30.604392 | I6: 0 | J6: =SUM(E6:I6) -> 697.78379 | K6: =D6+J6 -> 4594.3338 | L6: =K6/'Quellen & Annahmen'!$B$2 -> 0.041615007 | M6: Direkt; boerse.de-Aktienfonds; boerse.de-Technologiefonds (60% offengelegt); MSCI World | N6: Nutzerangaben im Chat; https://www.boerse-aktienfonds.de/; https://www.boerse-technologiefonds.de/; https://www.ishares.com/ch/individual/en/products/251882/ishares-msci-world-ucits-etf-acc-fund
A7: 6 | B7: Microsoft | C7: Information Technology | D7: 2410.1 | E7: 573.75232 | F7: 1036.472 | G7: 90.219784 | H7: 105.93828 | I7: 0 | J7: =SUM(E7:I7) -> 1806.3823 | K7: =D7+J7 -> 4216.4823 | L7: =K7/'Quellen & Annahmen'!$B$2 -> 0.038192467 | M7: Direkt; boerse.de-Aktienfonds; Global Titans 50; boerse.de-Technologiefonds (60% offengelegt); MSCI World | N7: Nutzerangaben im Chat; https://www.boerse-aktienfonds.de/; https://www.ishares.com/ch/professionals/en/products/251769/ishares-dow-jones-global-titans-50-ucits-etf-de-fund; https://www.boerse-technologiefonds.de/; https://www.ishares.com/ch/individual/en/products/251882/ishares-msci-world-ucits-etf-acc-fund
A8: 7 | B8: Apple | C8: Information Technology | D8: 1458.25 | E8: 615.1246 | F8: 1173.5151 | G8: 96.714621 | H8: 182.95373 | I8: 0 | J8: =SUM(E8:I8) -> 2068.3081 | K8: =D8+J8 -> 3526.5581 | L8: =K8/'Quellen & Annahmen'!$B$2 -> 0.031943203 | M8: Direkt; boerse.de-Aktienfonds; Global Titans 50; boerse.de-Technologiefonds (60% offengelegt); MSCI World | N8: Nutzerangaben im Chat; https://www.boerse-aktienfonds.de/; https://www.ishares.com/ch/professionals/en/products/251769/ishares-dow-jones-global-titans-50-ucits-etf-de-fund; https://www.boerse-technologiefonds.de/; https://www.ishares.com/ch/individual/en/products/251882/ishares-msci-world-ucits-etf-acc-fund
A9: 8 | B9: Eli Lilly | C9: Health Care | D9: 2060.8 | E9: 536.35595 | F9: 361.90035 | G9: 0 | H9: 34.976448 | I9: 0 | J9: =SUM(E9:I9) -> 933.23275 | K9: =D9+J9 -> 2994.0328 | L9: =K9/'Quellen & Annahmen'!$B$2 -> 0.027119643 | M9: Direkt; boerse.de-Aktienfonds; Global Titans 50; MSCI World | N9: Nutzerangaben im Chat; https://www.boerse-aktienfonds.de/; https://www.ishares.com/ch/professionals/en/products/251769/ishares-dow-jones-global-titans-50-ucits-etf-de-fund; https://www.ishares.com/ch/individual/en/products/251882/ishares-msci-world-ucits-etf-acc-fund
A10: 9 | B10: TSMC | C10: Information Technology | D10: 696 | E10: 529.24686 | F10: 723.8007 | G10: 71.769335 | H10: 0 | I10: 0 | J10: =SUM(E10:I10) -> 1324.8169 | K10: =D10+J10 -> 2020.8169 | L10: =K10/'Quellen & Annahmen'!$B$2 -> 0.018304353 | M10: Direkt; boerse.de-Aktienfonds; Global Titans 50; boerse.de-Technologiefonds (60% offengelegt) | N10: Nutzerangaben im Chat; https://www.boerse-aktienfonds.de/; https://www.ishares.com/ch/professionals/en/products/251769/ishares-dow-jones-global-titans-50-ucits-etf-de-fund; https://www.boerse-technologiefonds.de/
A11: 10 | B11: Siemens | D11: 1851.5 | E11: 0 | F11: 0 | G11: 80.610658 | H11: 0 | I11: 0 | J11: =SUM(E11:I11) -> 80.610658 | K11: =D11+J11 -> 1932.1107 | L11: =K11/'Quellen & Annahmen'!$B$2 -> 0.017500861 | M11: Direkt; boerse.de-Technologiefonds (60% offengelegt) | N11: Nutzerangaben im Chat; https://www.boerse-technologiefonds.de/
A12: 11 | B12: HSBC | C12: Financials | D12: 1702.16 | E12: 0 | F12: 135.71263 | G12: 0 | H12: 12.779856 | I12: 11.524504 | J12: =SUM(E12:I12) -> 160.01699 | K12: =D12+J12 -> 1862.177 | L12: =K12/'Quellen & Annahmen'!$B$2 -> 0.016867409 | M12: Direkt; Global Titans 50; MSCI World; World Value | N12: Nutzerangaben im Chat; https://www.ishares.com/ch/professionals/en/products/251769/ishares-dow-jones-global-titans-50-ucits-etf-de-fund; https://www.ishares.com/ch/individual/en/products/251882/ishares-msci-world-ucits-etf-acc-fund; https://www.ishares.com/ch/individual/en/products/270048/ishares-msci-world-value-factor-ucits-etf
A13: 12 | B13: Amazon | C13: Consumer Discretionary | D13: 0 | E13: 567.84793 | F13: 959.30204 | G13: 88.057173 | H13: 90.467928 | I13: 0 | J13: =SUM(E13:I13) -> 1705.6751 | K13: =D13+J13 -> 1705.6751 | L13: =K13/'Quellen & Annahmen'!$B$2 -> 0.015449831 | M13: boerse.de-Aktienfonds; Global Titans 50; boerse.de-Technologiefonds (60% offengelegt); MSCI World | N13: https://www.boerse-aktienfonds.de/; https://www.ishares.com/ch/professionals/en/products/251769/ishares-dow-jones-global-titans-50-ucits-etf-de-fund; https://www.boerse-technologiefonds.de/; https://www.ishares.com/ch/individual/en/products/251882/ishares-msci-world-ucits-etf-acc-fund
A14: 13 | B14: Micron Technology | C14: Information Technology | D14: 1492.2 | E14: 0 | F14: 0 | G14: 0 | H14: 35.985384 | I14: 150.50318 | J14: =SUM(E14:I14) -> 186.48856 | K14: =D14+J14 -> 1678.6886 | L14: =K14/'Quellen & Annahmen'!$B$2 -> 0.01520539 | M14: Direkt; MSCI World; World Value | N14: Nutzerangaben im Chat; https://www.ishares.com/ch/individual/en/products/251882/ishares-msci-world-ucits-etf-acc-fund; https://www.ishares.com/ch/individual/en/products/270048/ishares-msci-world-value-factor-ucits-etf
A15: 14 | B15: Linde | C15: Materials | D15: 896.8 | E15: 0 | F15: 94.466636 | G15: 0 | H15: 9.080424 | I15: 0 | J15: =SUM(E15:I15) -> 103.54706 | K15: =D15+J15 -> 1000.3471 | L15: =K15/'Quellen & Annahmen'!$B$2 -> 0.0090610416 | M15: Direkt; Global Titans 50; MSCI World | N15: Nutzerangaben im Chat; https://www.ishares.com/ch/professionals/en/products/251769/ishares-dow-jones-global-titans-50-ucits-etf-de-fund; https://www.ishares.com/ch/individual/en/products/251882/ishares-msci-world-ucits-etf-acc-fund
A16: 15 | B16: ASML | C16: Information Technology | D16: 0 | E16: 548.22921 | F16: 278.07784 | G16: 78.312211 | H16: 26.568648 | I16: 0 | J16: =SUM(E16:I16) -> 931.18791 | K16: =D16+J16 -> 931.18791 | L16: =K16/'Quellen & Annahmen'!$B$2 -> 0.0084346051 | M16: boerse.de-Aktienfonds; Global Titans 50; boerse.de-Technologiefonds (60% offengelegt); MSCI World | N16: https://www.boerse-aktienfonds.de/; https://www.ishares.com/ch/professionals/en/products/251769/ishares-dow-jones-global-titans-50-ucits-etf-de-fund; https://www.boerse-technologiefonds.de/; https://www.ishares.com/ch/individual/en/products/251882/ishares-msci-world-ucits-etf-acc-fund
A17: 16 | B17: Broadcom | C17: Information Technology | D17: 0 | E17: 0 | F17: 694.52935 | G17: 83.019604 | H17: 62.890344 | I17: 0 | J17: =SUM(E17:I17) -> 840.4393 | K17: =D17+J17 -> 840.4393 | L17: =K17/'Quellen & Annahmen'!$B$2 -> 0.0076126135 | M17: Global Titans 50; boerse.de-Technologiefonds (60% offengelegt); MSCI World | N17: https://www.ishares.com/ch/professionals/en/products/251769/ishares-dow-jones-global-titans-50-ucits-etf-de-fund; https://www.boerse-technologiefonds.de/; https://www.ishares.com/ch/individual/en/products/251882/ishares-msci-world-ucits-etf-acc-fund
A18: 17 | B18: Visa | C18: Financials | D18: 0 | E18: 561.19738 | F18: 238.16236 | G18: 0 | H18: 22.869216 | I18: 0 | J18: =SUM(E18:I18) -> 822.22896 | K18: =D18+J18 -> 822.22896 | L18: =K18/'Quellen & Annahmen'!$B$2 -> 0.007447666 | M18: boerse.de-Aktienfonds; Global Titans 50; MSCI World | N18: https://www.boerse-aktienfonds.de/; https://www.ishares.com/ch/professionals/en/products/251769/ishares-dow-jones-global-titans-50-ucits-etf-de-fund; https://www.ishares.com/ch/individual/en/products/251882/ishares-msci-world-ucits-etf-acc-fund
A19: 18 | B19: Netflix | C19: Communication | D19: 0 | E19: 545.7117 | F19: 122.40747 | G19: 86.993496 | H19: 11.77092 | I19: 0 | J19: =SUM(E19:I19) -> 766.88359 | K19: =D19+J19 -> 766.88359 | L19: =K19/'Quellen & Annahmen'!$B$2 -> 0.0069463533 | M19: boerse.de-Aktienfonds; Global Titans 50; boerse.de-Technologiefonds (60% offengelegt); MSCI World | N19: https://www.boerse-aktienfonds.de/; https://www.ishares.com/ch/professionals/en/products/251769/ishares-dow-jones-global-titans-50-ucits-etf-de-fund; https://www.boerse-technologiefonds.de/; https://www.ishares.com/ch/individual/en/products/251882/ishares-msci-world-ucits-etf-acc-fund
A20: 19 | B20: Mastercard | C20: Financials | D20: 0 | E20: 569.70225 | F20: 174.2976 | G20: 0 | H20: 16.8156 | I20: 0 | J20: =SUM(E20:I20) -> 760.81545 | K20: =D20+J20 -> 760.81545 | L20: =K20/'Quellen & Annahmen'!$B$2 -> 0.0068913887 | M20: boerse.de-Aktienfonds; Global Titans 50; MSCI World | N20: https://www.boerse-aktienfonds.de/; https://www.ishares.com/ch/professionals/en/products/251769/ishares-dow-jones-global-titans-50-ucits-etf-de-fund; https://www.ishares.com/ch/individual/en/products/251882/ishares-msci-world-ucits-etf-acc-fund
A21: 20 | B21: SAP | C21: Information Technology | D21: 0 | E21: 560.15032 | F21: 62.534252 | G21: 85.875411 | H21: 6.053616 | I21: 0 | J21: =SUM(E21:I21) -> 714.6136 | K21: =D21+J21 -> 714.6136 | L21: =K21/'Quellen & Annahmen'!$B$2 -> 0.0064728971 | M21: boerse.de-Aktienfonds; Global Titans 50; boerse.de-Technologiefonds (60% offengelegt); MSCI World | N21: https://www.boerse-aktienfonds.de/; https://www.ishares.com/ch/professionals/en/products/251769/ishares-dow-jones-global-titans-50-ucits-etf-de-fund; https://www.boerse-technologiefonds.de/; https://www.ishares.com/ch/individual/en/products/251882/ishares-msci-world-ucits-etf-acc-fund
A22: 21 | B22: T-Mobile US | D22: 0 | E22: 592.34453 | F22: 0 | G22: 95.894458 | H22: 0 | I22: 0 | J22: =SUM(E22:I22) -> 688.23899 | K22: =D22+J22 -> 688.23899 | L22: =K22/'Quellen & Annahmen'!$B$2 -> 0.0062339985 | M22: boerse.de-Aktienfonds; boerse.de-Technologiefonds (60% offengelegt) | N22: https://www.boerse-aktienfonds.de/; https://www.boerse-technologiefonds.de/
A23: 22 | B23: Caterpillar | C23: Industrials | D23: 0 | E23: 514.4086 | F23: 158.3314 | G23: 0 | H23: 15.13404 | I23: 0 | J23: =SUM(E23:I23) -> 687.87404 | K23: =D23+J23 -> 687.87404 | L23: =K23/'Quellen & Annahmen'!$B$2 -> 0.0062306929 | M23: boerse.de-Aktienfonds; Global Titans 50; MSCI World | N23: https://www.boerse-aktienfonds.de/; https://www.ishares.com/ch/professionals/en/products/251769/ishares-dow-jones-global-titans-50-ucits-etf-de-fund; https://www.ishares.com/ch/individual/en/products/251882/ishares-msci-world-ucits-etf-acc-fund
A24: 23 | B24: McDonald's | C24: Consumer Discretionary | D24: 0 | E24: 564.08635 | F24: 75.839412 | G24: 0 | H24: 7.398864 | I24: 0 | J24: =SUM(E24:I24) -> 647.32463 | K24: =D24+J24 -> 647.32463 | L24: =K24/'Quellen & Annahmen'!$B$2 -> 0.0058634005 | M24: boerse.de-Aktienfonds; Global Titans 50; MSCI World | N24: https://www.boerse-aktienfonds.de/; https://www.ishares.com/ch/professionals/en/products/251769/ishares-dow-jones-global-titans-50-ucits-etf-de-fund; https://www.ishares.com/ch/individual/en/products/251882/ishares-msci-world-ucits-etf-acc-fund
A25: 24 | B25: Booking Holdings | C25: Consumer Discretionary | D25: 0 | E25: 543.19522 | F25: 0 | G25: 86.960697 | H25: 5.717304 | I25: 0 | J25: =SUM(E25:I25) -> 635.87322 | K25: =D25+J25 -> 635.87322 | L25: =K25/'Quellen & Annahmen'!$B$2 -> 0.0057596747 | M25: boerse.de-Aktienfonds; boerse.de-Technologiefonds (60% offengelegt); MSCI World | N25: https://www.boerse-aktienfonds.de/; https://www.boerse-technologiefonds.de/; https://www.ishares.com/ch/individual/en/products/251882/ishares-msci-world-ucits-etf-acc-fund
A26: 25 | B26: Nasdaq Inc. | C26: Financials | D26: 0 | E26: 629.36552 | F26: 0 | G26: 0 | H26: 1.68156 | I26: 0 | J26: =SUM(E26:I26) -> 631.04708 | K26: =D26+J26 -> 631.04708 | L26: =K26/'Quellen & Annahmen'!$B$2 -> 0.0057159601 | M26: boerse.de-Aktienfonds; MSCI World | N26: https://www.boerse-aktienfonds.de/; https://www.ishares.com/ch/individual/en/products/251882/ishares-msci-world-ucits-etf-acc-fund
A27: 26 | B27: Meta Platforms | C27: Communication | D27: 0 | E27: 0 | F27: 572.12188 | G27: 0 | H27: 54.482544 | I27: 0 | J27: =SUM(E27:I27) -> 626.60442 | K27: =D27+J27 -> 626.60442 | L27: =K27/'Quellen & Annahmen'!$B$2 -> 0.005675719 | M27: Global Titans 50; MSCI World | N27: https://www.ishares.com/ch/professionals/en/products/251769/ishares-dow-jones-global-titans-50-ucits-etf-de-fund; https://www.ishares.com/ch/individual/en/products/251882/ishares-msci-world-ucits-etf-acc-fund
A28: 27 | B28: LVMH | C28: Consumer Discretionary | D28: 0 | E28: 558.67546 | F28: 57.212188 | G28: 0 | H28: 5.380992 | I28: 0 | J28: =SUM(E28:I28) -> 621.26864 | K28: =D28+J28 -> 621.26864 | L28: =K28/'Quellen & Annahmen'!$B$2 -> 0.0056273879 | M28: boerse.de-Aktienfonds; Global Titans 50; MSCI World | N28: https://www.boerse-aktienfonds.de/; https://www.ishares.com/ch/professionals/en/products/251769/ishares-dow-jones-global-titans-50-ucits-etf-de-fund; https://www.ishares.com/ch/individual/en/products/251882/ishares-msci-world-ucits-etf-acc-fund
A29: 28 | B29: Amphenol | C29: Information Technology | D29: 0 | E29: 531.62759 | F29: 0 | G29: 72.441105 | H29: 7.062552 | I29: 0 | J29: =SUM(E29:I29) -> 611.13125 | K29: =D29+J29 -> 611.13125 | L29: =K29/'Quellen & Annahmen'!$B$2 -> 0.0055355645 | M29: boerse.de-Aktienfonds; boerse.de-Technologiefonds (60% offengelegt); MSCI World | N29: https://www.boerse-aktienfonds.de/; https://www.boerse-technologiefonds.de/; https://www.ishares.com/ch/individual/en/products/251882/ishares-msci-world-ucits-etf-acc-fund
A30: 29 | B30: BlackRock | C30: Financials | D30: 0 | E30: 598.71983 | F30: 0 | G30: 0 | H30: 6.053616 | I30: 0 | J30: =SUM(E30:I30) -> 604.77345 | K30: =D30+J30 -> 604.77345 | L30: =K30/'Quellen & Annahmen'!$B$2 -> 0.0054779762 | M30: boerse.de-Aktienfonds; MSCI World | N30: https://www.boerse-aktienfonds.de/; https://www.ishares.com/ch/individual/en/products/251882/ishares-msci-world-ucits-etf-acc-fund
A31: 30 | B31: MSCI Inc. | C31: Financials | D31: 0 | E31: 591.31512 | F31: 0 | G31: 0 | H31: 1.68156 | I31: 0 | J31: =SUM(E31:I31) -> 592.99668 | K31: =D31+J31 -> 592.99668 | L31: =K31/'Quellen & Annahmen'!$B$2 -> 0.0053713035 | M31: boerse.de-Aktienfonds; MSCI World | N31: https://www.boerse-aktienfonds.de/; https://www.ishares.com/ch/individual/en/products/251882/ishares-msci-world-ucits-etf-acc-fund
A32: 31 | B32: Cintas | C32: Industrials | D32: 0 | E32: 583.5963 | F32: 0 | G32: 0 | H32: 2.690496 | I32: 0 | J32: =SUM(E32:I32) -> 586.2868 | K32: =D32+J32 -> 586.2868 | L32: =K32/'Quellen & Annahmen'!$B$2 -> 0.005310526 | M32: boerse.de-Aktienfonds; MSCI World | N32: https://www.boerse-aktienfonds.de/; https://www.ishares.com/ch/individual/en/products/251882/ishares-msci-world-ucits-etf-acc-fund
A33: 32 | B33: S&P Global | C33: Financials | D33: 0 | E33: 578.83349 | F33: 0 | G33: 0 | H33: 5.380992 | I33: 0 | J33: =SUM(E33:I33) -> 584.21448 | K33: =D33+J33 -> 584.21448 | L33: =K33/'Quellen & Annahmen'!$B$2 -> 0.0052917552 | M33: boerse.de-Aktienfonds; MSCI World | N33: https://www.boerse-aktienfonds.de/; https://www.ishares.com/ch/individual/en/products/251882/ishares-msci-world-ucits-etf-acc-fund
A34: 33 | B34: Waste Management | C34: Industrials | D34: 0 | E34: 580.23267 | F34: 0 | G34: 0 | H34: 3.699432 | I34: 0 | J34: =SUM(E34:I34) -> 583.9321 | K34: =D34+J34 -> 583.9321 | L34: =K34/'Quellen & Annahmen'!$B$2 -> 0.0052891974 | M34: boerse.de-Aktienfonds; MSCI World | N34: https://www.boerse-aktienfonds.de/; https://www.ishares.com/ch/individual/en/products/251882/ishares-msci-world-ucits-etf-acc-fund
A35: 34 | B35: Danaher | C35: Health Care | D35: 0 | E35: 573.57091 | F35: 0 | G35: 0 | H35: 4.708368 | I35: 0 | J35: =SUM(E35:I35) -> 578.27928 | K35: =D35+J35 -> 578.27928 | L35: =K35/'Quellen & Annahmen'!$B$2 -> 0.0052379947 | M35: boerse.de-Aktienfonds; MSCI World | N35: https://www.boerse-aktienfonds.de/; https://www.ishares.com/ch/individual/en/products/251882/ishares-msci-world-ucits-etf-acc-fund
A36: 35 | B36: Hannover Rück | D36: 0 | E36: 577.23593 | F36: 0 | G36: 0 | H36: 0 | I36: 0 | J36: =SUM(E36:I36) -> 577.23593 | K36: =D36+J36 -> 577.23593 | L36: =K36/'Quellen & Annahmen'!$B$2 -> 0.0052285442 | M36: boerse.de-Aktienfonds | N36: https://www.boerse-aktienfonds.de/
A37: 36 | B37: Deutsche Börse | C37: Financials | D37: 0 | E37: 573.61707 | F37: 0 | G37: 0 | H37: 2.017872 | I37: 0 | J37: =SUM(E37:I37) -> 575.63494 | K37: =D37+J37 -> 575.63494 | L37: =K37/'Quellen & Annahmen'!$B$2 -> 0.0052140426 | M37: boerse.de-Aktienfonds; MSCI World | N37: https://www.boerse-aktienfonds.de/; https://www.ishares.com/ch/individual/en/products/251882/ishares-msci-world-ucits-etf-acc-fund
A38: 37 | B38: Walmart | C38: Consumer Staples | D38: 0 | E38: 551.96007 | F38: 0 | G38: 0 | H38: 18.833472 | I38: 0 | J38: =SUM(E38:I38) -> 570.79355 | K38: =D38+J38 -> 570.79355 | L38: =K38/'Quellen & Annahmen'!$B$2 -> 0.0051701897 | M38: boerse.de-Aktienfonds; MSCI World | N38: https://www.boerse-aktienfonds.de/; https://www.ishares.com/ch/individual/en/products/251882/ishares-msci-world-ucits-etf-acc-fund
A39: 38 | B39: Yum! Brands | C39: Consumer Discretionary | D39: 0 | E39: 565.36064 | F39: 0 | G39: 0 | H39: 1.68156 | I39: 0 | J39: =SUM(E39:I39) -> 567.0422 | K39: =D39+J39 -> 567.0422 | L39: =K39/'Quellen & Annahmen'!$B$2 -> 0.0051362104 | M39: boerse.de-Aktienfonds; MSCI World | N39: https://www.boerse-aktienfonds.de/; https://www.ishares.com/ch/individual/en/products/251882/ishares-msci-world-ucits-etf-acc-fund
A40: 39 | B40: TJX Companies | C40: Consumer Discretionary | D40: 0 | E40: 555.88134 | F40: 0 | G40: 0 | H40: 6.389928 | I40: 0 | J40: =SUM(E40:I40) -> 562.27127 | K40: =D40+J40 -> 562.27127 | L40: =K40/'Quellen & Annahmen'!$B$2 -> 0.0050929958 | M40: boerse.de-Aktienfonds; MSCI World | N40: https://www.boerse-aktienfonds.de/; https://www.ishares.com/ch/individual/en/products/251882/ishares-msci-world-ucits-etf-acc-fund
A41: 40 | B41: Home Depot | C41: Consumer Discretionary | D41: 0 | E41: 543.66257 | F41: 0 | G41: 0 | H41: 13.116168 | I41: 0 | J41: =SUM(E41:I41) -> 556.77874 | K41: =D41+J41 -> 556.77874 | L41: =K41/'Quellen & Annahmen'!$B$2 -> 0.005043245 | M41: boerse.de-Aktienfonds; MSCI World | N41: https://www.boerse-aktienfonds.de/; https://www.ishares.com/ch/individual/en/products/251882/ishares-msci-world-ucits-etf-acc-fund
A42: 41 | B42: Stryker | C42: Health Care | D42: 0 | E42: 549.54524 | F42: 0 | G42: 0 | H42: 4.035744 | I42: 0 | J42: =SUM(E42:I42) -> 553.58098 | K42: =D42+J42 -> 553.58098 | L42: =K42/'Quellen & Annahmen'!$B$2 -> 0.0050142801 | M42: boerse.de-Aktienfonds; MSCI World | N42: https://www.boerse-aktienfonds.de/; https://www.ishares.com/ch/individual/en/products/251882/ishares-msci-world-ucits-etf-acc-fund
A43: 42 | B43: Costco Wholesale | C43: Consumer Staples | D43: 0 | E43: 537.49074 | F43: 0 | G43: 0 | H43: 15.806664 | I43: 0 | J43: =SUM(E43:I43) -> 553.2974 | K43: =D43+J43 -> 553.2974 | L43: =K43/'Quellen & Annahmen'!$B$2 -> 0.0050117114 | M43: boerse.de-Aktienfonds; MSCI World | N43: https://www.boerse-aktienfonds.de/; https://www.ishares.com/ch/individual/en/products/251882/ishares-msci-world-ucits-etf-acc-fund
A44: 43 | B44: L'Oréal | C44: Consumer Staples | D44: 0 | E44: 546.53594 | F44: 0 | G44: 0 | H44: 3.699432 | I44: 0 | J44: =SUM(E44:I44) -> 550.23537 | K44: =D44+J44 -> 550.23537 | L44: =K44/'Quellen & Annahmen'!$B$2 -> 0.0049839759 | M44: boerse.de-Aktienfonds; MSCI World | N44: https://www.boerse-aktienfonds.de/; https://www.ishares.com/ch/individual/en/products/251882/ishares-msci-world-ucits-etf-acc-fund
A45: 44 | B45: Ecolab | C45: Materials | D45: 0 | E45: 546.94254 | F45: 0 | G45: 0 | H45: 2.690496 | I45: 0 | J45: =SUM(E45:I45) -> 549.63304 | K45: =D45+J45 -> 549.63304 | L45: =K45/'Quellen & Annahmen'!$B$2 -> 0.00497852 | M45: boerse.de-Aktienfonds; MSCI World | N45: https://www.boerse-aktienfonds.de/; https://www.ishares.com/ch/individual/en/products/251882/ishares-msci-world-ucits-etf-acc-fund
A46: 45 | B46: Lindt & Sprüngli | D46: 0 | E46: 542.69375 | F46: 0 | G46: 0 | H46: 0 | I46: 0 | J46: =SUM(E46:I46) -> 542.69375 | K46: =D46+J46 -> 542.69375 | L46: =K46/'Quellen & Annahmen'!$B$2 -> 0.0049156646 | M46: boerse.de-Aktienfonds | N46: https://www.boerse-aktienfonds.de/
A47: 46 | B47: Autozone | D47: 0 | E47: 541.47225 | F47: 0 | G47: 0 | H47: 0 | I47: 0 | J47: =SUM(E47:I47) -> 541.47225 | K47: =D47+J47 -> 541.47225 | L47: =K47/'Quellen & Annahmen'!$B$2 -> 0.0049046004 | M47: boerse.de-Aktienfonds | N47: https://www.boerse-aktienfonds.de/
A48: 47 | B48: Tesla | C48: Consumer Discretionary | D48: 0 | E48: 0 | F48: 431.08718 | G48: 0 | H48: 41.030064 | I48: 0 | J48: =SUM(E48:I48) -> 472.11725 | K48: =D48+J48 -> 472.11725 | L48: =K48/'Quellen & Annahmen'!$B$2 -> 0.0042763899 | M48: Global Titans 50; MSCI World | N48: https://www.ishares.com/ch/professionals/en/products/251769/ishares-dow-jones-global-titans-50-ucits-etf-de-fund; https://www.ishares.com/ch/individual/en/products/251882/ishares-msci-world-ucits-etf-acc-fund
A49: 48 | B49: JPMorgan Chase | C49: Financials | D49: 0 | E49: 0 | F49: 360.56984 | G49: 0 | H49: 34.303824 | I49: 0 | J49: =SUM(E49:I49) -> 394.87366 | K49: =D49+J49 -> 394.87366 | L49: =K49/'Quellen & Annahmen'!$B$2 -> 0.0035767253 | M49: Global Titans 50; MSCI World | N49: https://www.ishares.com/ch/professionals/en/products/251769/ishares-dow-jones-global-titans-50-ucits-etf-de-fund; https://www.ishares.com/ch/individual/en/products/251882/ishares-msci-world-ucits-etf-acc-fund
A50: 49 | B50: Samsung Electronics Ltd | C50: Information Technology | D50: 0 | E50: 0 | F50: 331.29848 | G50: 0 | H50: 0 | I50: 0 | J50: =SUM(E50:I50) -> 331.29848 | K50: =D50+J50 -> 331.29848 | L50: =K50/'Quellen & Annahmen'!$B$2 -> 0.0030008679 | M50: Global Titans 50 | N50: https://www.ishares.com/ch/professionals/en/products/251769/ishares-dow-jones-global-titans-50-ucits-etf-de-fund
A51: 50 | B51: Exxonmobil Holdings Corp | C51: Energy | D51: 0 | E51: 0 | F51: 236.83185 | G51: 0 | H51: 22.869216 | I51: 0 | J51: =SUM(E51:I51) -> 259.70106 | K51: =D51+J51 -> 259.70106 | L51: =K51/'Quellen & Annahmen'!$B$2 -> 0.0023523457 | M51: Global Titans 50; MSCI World | N51: https://www.ishares.com/ch/professionals/en/products/251769/ishares-dow-jones-global-titans-50-ucits-etf-de-fund; https://www.ishares.com/ch/individual/en/products/251882/ishares-msci-world-ucits-etf-acc-fund
A52: 51 | B52: Johnson & Johnson | C52: Health Care | D52: 0 | E52: 0 | F52: 235.50133 | G52: 0 | H52: 22.532904 | I52: 0 | J52: =SUM(E52:I52) -> 258.03424 | K52: =D52+J52 -> 258.03424 | L52: =K52/'Quellen & Annahmen'!$B$2 -> 0.0023372478 | M52: Global Titans 50; MSCI World | N52: https://www.ishares.com/ch/professionals/en/products/251769/ishares-dow-jones-global-titans-50-ucits-etf-de-fund; https://www.ishares.com/ch/individual/en/products/251882/ishares-msci-world-ucits-etf-acc-fund
A53: 52 | B53: Cisco Systems Inc | C53: Information Technology | D53: 0 | E53: 0 | F53: 170.30605 | G53: 0 | H53: 16.142976 | I53: 35.486344 | J53: =SUM(E53:I53) -> 221.93537 | K53: =D53+J53 -> 221.93537 | L53: =K53/'Quellen & Annahmen'!$B$2 -> 0.0020102679 | M53: Global Titans 50; MSCI World; World Value | N53: https://www.ishares.com/ch/professionals/en/products/251769/ishares-dow-jones-global-titans-50-ucits-etf-de-fund; https://www.ishares.com/ch/individual/en/products/251882/ishares-msci-world-ucits-etf-acc-fund; https://www.ishares.com/ch/individual/en/products/270048/ishares-msci-world-value-factor-ucits-etf
A54: 53 | B54: Abbvie Inc | C54: Health Care | D54: 0 | E54: 0 | F54: 175.62811 | G54: 0 | H54: 16.8156 | I54: 0 | J54: =SUM(E54:I54) -> 192.44371 | K54: =D54+J54 -> 192.44371 | L54: =K54/'Quellen & Annahmen'!$B$2 -> 0.0017431355 | M54: Global Titans 50; MSCI World | N54: https://www.ishares.com/ch/professionals/en/products/251769/ishares-dow-jones-global-titans-50-ucits-etf-de-fund; https://www.ishares.com/ch/individual/en/products/251882/ishares-msci-world-ucits-etf-acc-fund
A55: 54 | B55: Ge Aerospace | C55: Industrials | D55: 0 | E55: 0 | F55: 141.0347 | G55: 0 | H55: 13.45248 | I55: 0 | J55: =SUM(E55:I55) -> 154.48718 | K55: =D55+J55 -> 154.48718 | L55: =K55/'Quellen & Annahmen'!$B$2 -> 0.0013993291 | M55: Global Titans 50; MSCI World | N55: https://www.ishares.com/ch/professionals/en/products/251769/ishares-dow-jones-global-titans-50-ucits-etf-de-fund; https://www.ishares.com/ch/individual/en/products/251882/ishares-msci-world-ucits-etf-acc-fund
A56: 55 | B56: Procter & Gamble | C56: Consumer Staples | D56: 0 | E56: 0 | F56: 138.37366 | G56: 0 | H56: 13.116168 | I56: 0 | J56: =SUM(E56:I56) -> 151.48983 | K56: =D56+J56 -> 151.48983 | L56: =K56/'Quellen & Annahmen'!$B$2 -> 0.0013721794 | M56: Global Titans 50; MSCI World | N56: https://www.ishares.com/ch/professionals/en/products/251769/ishares-dow-jones-global-titans-50-ucits-etf-de-fund; https://www.ishares.com/ch/individual/en/products/251882/ishares-msci-world-ucits-etf-acc-fund
A57: 56 | B57: Chevron Corp | C57: Energy | D57: 0 | E57: 0 | F57: 134.38212 | G57: 0 | H57: 12.779856 | I57: 0 | J57: =SUM(E57:I57) -> 147.16197 | K57: =D57+J57 -> 147.16197 | L57: =K57/'Quellen & Annahmen'!$B$2 -> 0.0013329781 | M57: Global Titans 50; MSCI World | N57: https://www.ishares.com/ch/professionals/en/products/251769/ishares-dow-jones-global-titans-50-ucits-etf-de-fund; https://www.ishares.com/ch/individual/en/products/251882/ishares-msci-world-ucits-etf-acc-fund
A58: 57 | B58: Coca-Cola | C58: Consumer Staples | D58: 0 | E58: 0 | F58: 129.06005 | G58: 0 | H58: 12.443544 | I58: 0 | J58: =SUM(E58:I58) -> 141.5036 | K58: =D58+J58 -> 141.5036 | L58: =K58/'Quellen & Annahmen'!$B$2 -> 0.0012817251 | M58: Global Titans 50; MSCI World | N58: https://www.ishares.com/ch/professionals/en/products/251769/ishares-dow-jones-global-titans-50-ucits-etf-de-fund; https://www.ishares.com/ch/individual/en/products/251882/ishares-msci-world-ucits-etf-acc-fund
A59: 58 | B59: Goldman Sachs Group Inc | C59: Financials | D59: 0 | E59: 0 | F59: 127.72954 | G59: 0 | H59: 12.107232 | I59: 0 | J59: =SUM(E59:I59) -> 139.83677 | K59: =D59+J59 -> 139.83677 | L59: =K59/'Quellen & Annahmen'!$B$2 -> 0.0012666272 | M59: Global Titans 50; MSCI World | N59: https://www.ishares.com/ch/professionals/en/products/251769/ishares-dow-jones-global-titans-50-ucits-etf-de-fund; https://www.ishares.com/ch/individual/en/products/251882/ishares-msci-world-ucits-etf-acc-fund
... A68: 67 | B68: Toyota Motor Corp | C68: Consumer Discretionary | D68: 0 | E68: 0 | F68: 82.491992 | G68: 0 | H68: 6.053616 | I68: 18.713056 | J68: =SUM(E68:I68) -> 107.25866 | K68: =D68+J68 -> 107.25866 | L68: =K68/'Quellen & Annahmen'!$B$2 -> 0.00097153804 | M68: Global Titans 50; MSCI World; World Value | N68: https://www.ishares.com/ch/professionals/en/products/251769/ishares-dow-jones-global-titans-50-ucits-etf-de-fund; https://www.ishares.com/ch/individual/en/products/251882/ishares-msci-world-ucits-etf-acc-fund; https://www.ishares.com/ch/individual/en/products/270048/ishares-msci-world-value-factor-ucits-etf
A69: 68 | B69: Mercadolibre | D69: 0 | E69: 0 | F69: 0 | G69: 91.931758 | H69: 0 | I69: 0 | J69: =SUM(E69:I69) -> 91.931758 | K69: =D69+J69 -> 91.931758 | L69: =K69/'Quellen & Annahmen'!$B$2 -> 0.00083270848 | M69: boerse.de-Technologiefonds (60% offengelegt) | N69: https://www.boerse-technologiefonds.de/
A70: 69 | B70: Texas Instruments | C70: Information Technology | D70: 0 | E70: 0 | F70: 0 | G70: 81.886234 | H70: 9.753048 | I70: 0 | J70: =SUM(E70:I70) -> 91.639282 | K70: =D70+J70 -> 91.639282 | L70: =K70/'Quellen & Annahmen'!$B$2 -> 0.00083005927 | M70: boerse.de-Technologiefonds (60% offengelegt); MSCI World | N70: https://www.boerse-technologiefonds.de/; https://www.ishares.com/ch/individual/en/products/251882/ishares-msci-world-ucits-etf-acc-fund
A71: 70 | B71: Constellation Software | C71: Information Technology | D71: 0 | E71: 0 | F71: 0 | G71: 89.889745 | H71: 1.345248 | I71: 0 | J71: =SUM(E71:I71) -> 91.234993 | K71: =D71+J71 -> 91.234993 | L71: =K71/'Quellen & Annahmen'!$B$2 -> 0.00082639726 | M71: boerse.de-Technologiefonds (60% offengelegt); MSCI World | N71: https://www.boerse-technologiefonds.de/; https://www.ishares.com/ch/individual/en/products/251882/ishares-msci-world-ucits-etf-acc-fund
A72: 71 | B72: Oracle Corp | C72: Information Technology | D72: 0 | E72: 0 | F72: 82.491992 | G72: 0 | H72: 8.071488 | I72: 0 | J72: =SUM(E72:I72) -> 90.56348 | K72: =D72+J72 -> 90.56348 | L72: =K72/'Quellen & Annahmen'!$B$2 -> 0.00082031476 | M72: Global Titans 50; MSCI World | N72: https://www.ishares.com/ch/professionals/en/products/251769/ishares-dow-jones-global-titans-50-ucits-etf-de-fund; https://www.ishares.com/ch/individual/en/products/251882/ishares-msci-world-ucits-etf-acc-fund
A73: 72 | B73: Arista Networks | C73: Information Technology | D73: 0 | E73: 0 | F73: 0 | G73: 83.35392 | H73: 6.72624 | I73: 0 | J73: =SUM(E73:I73) -> 90.08016 | K73: =D73+J73 -> 90.08016 | L73: =K73/'Quellen & Annahmen'!$B$2 -> 0.0008159369 | M73: boerse.de-Technologiefonds (60% offengelegt); MSCI World | N73: https://www.boerse-technologiefonds.de/; https://www.ishares.com/ch/individual/en/products/251882/ishares-msci-world-ucits-etf-acc-fund
A74: 73 | B74: International Business Machines Co | C74: Information Technology | D74: 0 | E74: 0 | F74: 81.161476 | G74: 0 | H74: 7.735176 | I74: 0 | J74: =SUM(E74:I74) -> 88.896652 | K74: =D74+J74 -> 88.896652 | L74: =K74/'Quellen & Annahmen'!$B$2 -> 0.00080521681 | M74: Global Titans 50; MSCI World | N74: https://www.ishares.com/ch/professionals/en/products/251769/ishares-dow-jones-global-titans-50-ucits-etf-de-fund; https://www.ishares.com/ch/individual/en/products/251882/ishares-msci-world-ucits-etf-acc-fund
A75: 74 | B75: Mettler-Toledo | C75: Health Care | D75: 0 | E75: 0 | F75: 0 | G75: 87.840453 | H75: 1.008936 | I75: 0 | J75: =SUM(E75:I75) -> 88.849389 | K75: =D75+J75 -> 88.849389 | L75: =K75/'Quellen & Annahmen'!$B$2 -> 0.0008047887 | M75: boerse.de-Technologiefonds (60% offengelegt); MSCI World | N75: https://www.boerse-technologiefonds.de/; https://www.ishares.com/ch/individual/en/products/251882/ishares-msci-world-ucits-etf-acc-fund
A76: 75 | B76: Nemetschek | C76: Information Technology | D76: 0 | E76: 0 | F76: 0 | G76: 88.477103 | H76: 0.336312 | I76: 0 | J76: =SUM(E76:I76) -> 88.813415 | K76: =D76+J76 -> 88.813415 | L76: =K76/'Quellen & Annahmen'!$B$2 -> 0.00080446286 | M76: boerse.de-Technologiefonds (60% offengelegt); MSCI World | N76: https://www.boerse-technologiefonds.de/; https://www.ishares.com/ch/individual/en/products/251882/ishares-msci-world-ucits-etf-acc-fund
A77: 76 | B77: FICO | C77: Information Technology | D77: 0 | E77: 0 | F77: 0 | G77: 87.190928 | H77: 1.008936 | I77: 0 | J77: =SUM(E77:I77) -> 88.199864 | K77: =D77+J77 -> 88.199864 | L77: =K77/'Quellen & Annahmen'!$B$2 -> 0.00079890537 | M77: boerse.de-Technologiefonds (60% offengelegt); MSCI World | N77: https://www.boerse-technologiefonds.de/; https://www.ishares.com/ch/individual/en/products/251882/ishares-msci-world-ucits-etf-acc-fund
A78: 77 | B78: Atoss Software | D78: 0 | E78: 0 | F78: 0 | G78: 87.774263 | H78: 0 | I78: 0 | J78: =SUM(E78:I78) -> 87.774263 | K78: =D78+J78 -> 87.774263 | L78: =K78/'Quellen & Annahmen'!$B$2 -> 0.00079505032 | M78: boerse.de-Technologiefonds (60% offengelegt) | N78: https://www.boerse-technologiefonds.de/
A79: 78 | B79: Thermo Fisher Scientific Inc | C79: Health Care | D79: 0 | E79: 0 | F79: 79.83096 | G79: 0 | H79: 7.735176 | I79: 0 | J79: =SUM(E79:I79) -> 87.566136 | K79: =D79+J79 -> 87.566136 | L79: =K79/'Quellen & Annahmen'!$B$2 -> 0.00079316513 | M79: Global Titans 50; MSCI World | N79: https://www.ishares.com/ch/professionals/en/products/251769/ishares-dow-jones-global-titans-50-ucits-etf-de-fund; https://www.ishares.com/ch/individual/en/products/251882/ishares-msci-world-ucits-etf-acc-fund
A80: 79 | B80: Servicenow | D80: 0 | E80: 0 | F80: 0 | G80: 87.53093 | H80: 0 | I80: 0 | J80: =SUM(E80:I80) -> 87.53093 | K80: =D80+J80 -> 87.53093 | L80: =K80/'Quellen & Annahmen'!$B$2 -> 0.00079284624 | M80: boerse.de-Technologiefonds (60% offengelegt) | N80: https://www.boerse-technologiefonds.de/
A81: 80 | B81: Elmos Semiconductor | D81: 0 | E81: 0 | F81: 0 | G81: 86.655314 | H81: 0 | I81: 0 | J81: =SUM(E81:I81) -> 86.655314 | K81: =D81+J81 -> 86.655314 | L81: =K81/'Quellen & Annahmen'!$B$2 -> 0.00078491499 | M81: boerse.de-Technologiefonds (60% offengelegt) | N81: https://www.boerse-technologiefonds.de/
A82: 81 | B82: Motorola Solutions | C82: Information Technology | D82: 0 | E82: 0 | F82: 0 | G82: 83.663261 | H82: 2.354184 | I82: 0 | J82: =SUM(E82:I82) -> 86.017445 | K82: =D82+J82 -> 86.017445 | L82: =K82/'Quellen & Annahmen'!$B$2 -> 0.00077913724 | M82: boerse.de-Technologiefonds (60% offengelegt); MSCI World | N82: https://www.boerse-technologiefonds.de/; https://www.ishares.com/ch/individual/en/products/251882/ishares-msci-world-ucits-etf-acc-fund
A83: 82 | B83: Cadence Design Systems | C83: Information Technology | D83: 0 | E83: 0 | F83: 0 | G83: 82.064515 | H83: 3.699432 | I83: 0 | J83: =SUM(E83:I83) -> 85.763947 | K83: =D83+J83 -> 85.763947 | L83: =K83/'Quellen & Annahmen'!$B$2 -> 0.00077684108 | M83: boerse.de-Technologiefonds (60% offengelegt); MSCI World | N83: https://www.boerse-technologiefonds.de/; https://www.ishares.com/ch/individual/en/products/251882/ishares-msci-world-ucits-etf-acc-fund
A84: 83 | B84: Ametek | C84: Industrials | D84: 0 | E84: 0 | F84: 0 | G84: 82.309349 | H84: 2.017872 | I84: 0 | J84: =SUM(E84:I84) -> 84.327221 | K84: =D84+J84 -> 84.327221 | L84: =K84/'Quellen & Annahmen'!$B$2 -> 0.00076382736 | M84: boerse.de-Technologiefonds (60% offengelegt); MSCI World | N84: https://www.boerse-technologiefonds.de/; https://www.ishares.com/ch/individual/en/products/251882/ishares-msci-world-ucits-etf-acc-fund
A85: 84 | B85: Axon Enterprise | C85: Industrials | D85: 0 | E85: 0 | F85: 0 | G85: 81.926722 | H85: 1.345248 | I85: 0 | J85: =SUM(E85:I85) -> 83.27197 | K85: =D85+J85 -> 83.27197 | L85: =K85/'Quellen & Annahmen'!$B$2 -> 0.00075426901 | M85: boerse.de-Technologiefonds (60% offengelegt); MSCI World | N85: https://www.boerse-technologiefonds.de/; https://www.ishares.com/ch/individual/en/products/251882/ishares-msci-world-ucits-etf-acc-fund
A86: 85 | B86: Monolithic Power Systems | C86: Information Technology | D86: 0 | E86: 0 | F86: 0 | G86: 79.467235 | H86: 2.354184 | I86: 0 | J86: =SUM(E86:I86) -> 81.821419 | K86: =D86+J86 -> 81.821419 | L86: =K86/'Quellen & Annahmen'!$B$2 -> 0.00074113007 | M86: boerse.de-Technologiefonds (60% offengelegt); MSCI World | N86: https://www.boerse-technologiefonds.de/; https://www.ishares.com/ch/individual/en/products/251882/ishares-msci-world-ucits-etf-acc-fund
A87: 86 | B87: Pepsico Inc | C87: Consumer Staples | D87: 0 | E87: 0 | F87: 74.508896 | G87: 0 | H87: 7.062552 | I87: 0 | J87: =SUM(E87:I87) -> 81.571448 | K87: =D87+J87 -> 81.571448 | L87: =K87/'Quellen & Annahmen'!$B$2 -> 0.00073886586 | M87: Global Titans 50; MSCI World | N87: https://www.ishares.com/ch/professionals/en/products/251769/ishares-dow-jones-global-titans-50-ucits-etf-de-fund; https://www.ishares.com/ch/individual/en/products/251882/ishares-msci-world-ucits-etf-acc-fund
A88: 87 | B88: Synopsys | C88: Information Technology | D88: 0 | E88: 0 | F88: 0 | G88: 78.484077 | H88: 3.026808 | I88: 0 | J88: =SUM(E88:I88) -> 81.510885 | K88: =D88+J88 -> 81.510885 | L88: =K88/'Quellen & Annahmen'!$B$2 -> 0.00073831728 | M88: boerse.de-Technologiefonds (60% offengelegt); MSCI World | N88: https://www.boerse-technologiefonds.de/; https://www.ishares.com/ch/individual/en/products/251882/ishares-msci-world-ucits-etf-acc-fund
A89: 88 | B89: Jabil | C89: Information Technology | D89: 0 | E89: 0 | F89: 0 | G89: 79.321162 | H89: 1.345248 | I89: 0 | J89: =SUM(E89:I89) -> 80.66641 | K89: =D89+J89 -> 80.66641 | L89: =K89/'Quellen & Annahmen'!$B$2 -> 0.00073066812 | M89: boerse.de-Technologiefonds (60% offengelegt); MSCI World | N89: https://www.boerse-technologiefonds.de/; https://www.ishares.com/ch/individual/en/products/251882/ishares-msci-world-ucits-etf-acc-fund
A90: 89 | B90: Lam Research | C90: Information Technology | D90: 0 | E90: 0 | F90: 0 | G90: 63.721425 | H90: 15.13404 | I90: 0 | J90: =SUM(E90:I90) -> 78.855465 | K90: =D90+J90 -> 78.855465 | L90: =K90/'Quellen & Annahmen'!$B$2 -> 0.00071426476 | M90: boerse.de-Technologiefonds (60% offengelegt); MSCI World | N90: https://www.boerse-technologiefonds.de/; https://www.ishares.com/ch/individual/en/products/251882/ishares-msci-world-ucits-etf-acc-fund
A91: 90 | B91: Abbott Laboratories | C91: Health Care | D91: 0 | E91: 0 | F91: 67.856316 | G91: 0 | H91: 6.389928 | I91: 0 | J91: =SUM(E91:I91) -> 74.246244 | K91: =D91+J91 -> 74.246244 | L91: =K91/'Quellen & Annahmen'!$B$2 -> 0.0006725149 | M91: Global Titans 50; MSCI World | N91: https://www.ishares.com/ch/professionals/en/products/251769/ishares-dow-jones-global-titans-50-ucits-etf-de-fund; https://www.ishares.com/ch/individual/en/products/251882/ishares-msci-world-ucits-etf-acc-fund
A92: 91 | B92: Pfizer Inc | C92: Health Care | D92: 0 | E92: 0 | F92: 55.881672 | G92: 0 | H92: 5.380992 | I92: 12.095024 | J92: =SUM(E92:I92) -> 73.357688 | K92: =D92+J92 -> 73.357688 | L92: =K92/'Quellen & Annahmen'!$B$2 -> 0.00066446645 | M92: Global Titans 50; MSCI World; World Value | N92: https://www.ishares.com/ch/professionals/en/products/251769/ishares-dow-jones-global-titans-50-ucits-etf-de-fund; https://www.ishares.com/ch/individual/en/products/251882/ishares-msci-world-ucits-etf-acc-fund; https://www.ishares.com/ch/individual/en/products/270048/ishares-msci-world-value-factor-ucits-etf
A93: 92 | B93: Novo Nordisk | C93: Health Care | D93: 0 | E93: 0 | F93: 63.864768 | G93: 0 | H93: 6.053616 | I93: 0 | J93: =SUM(E93:I93) -> 69.918384 | K93: =D93+J93 -> 69.918384 | L93: =K93/'Quellen & Annahmen'!$B$2 -> 0.00063331359 | M93: Global Titans 50; MSCI World | N93: https://www.ishares.com/ch/professionals/en/products/251769/ishares-dow-jones-global-titans-50-ucits-etf-de-fund; https://www.ishares.com/ch/individual/en/products/251882/ishares-msci-world-ucits-etf-acc-fund
... A1254: 1253 | B1254: Verisure Plc | C1254: Industrials | D1254: 0 | E1254: 0 | F1254: 0 | G1254: 0 | H1254: 0 | I1254: 0.114104 | J1254: =SUM(E1254:I1254) -> 0.114104 | K1254: =D1254+J1254 -> 0.114104 | L1254: =K1254/'Quellen & Annahmen'!$B$2 -> 1.0335424e-06 | M1254: World Value | N1254: https://www.ishares.com/ch/individual/en/products/270048/ishares-msci-world-value-factor-ucits-etf
A1255: 1254 | B1255: Demant | C1255: Health Care | D1255: 0 | E1255: 0 | F1255: 0 | G1255: 0 | H1255: 0 | I1255: 0 | J1255: =SUM(E1255:I1255) -> 0 | K1255: =D1255+J1255 -> 0 | L1255: =K1255/'Quellen & Annahmen'!$B$2 -> 0
A1256: 1255 | B1256: Edp Renewables Sa | C1256: Utilities | D1256: 0 | E1256: 0 | F1256: 0 | G1256: 0 | H1256: 0 | I1256: 0 | J1256: =SUM(E1256:I1256) -> 0 | K1256: =D1256+J1256 -> 0 | L1256: =K1256/'Quellen & Annahmen'!$B$2 -> 0
A1257: 1256 | B1257: Indra Sistemas Sa | C1257: Information Technology | D1257: 0 | E1257: 0 | F1257: 0 | G1257: 0 | H1257: 0 | I1257: 0 | J1257: =SUM(E1257:I1257) -> 0 | K1257: =D1257+J1257 -> 0 | L1257: =K1257/'Quellen & Annahmen'!$B$2 -> 0
A1258: 1257 | B1258: Toho (Tokyo) Ltd | C1258: Communication | D1258: 0 | E1258: 0 | F1258: 0 | G1258: 0 | H1258: 0 | I1258: 0 | J1258: =SUM(E1258:I1258) -> 0 | K1258: =D1258+J1258 -> 0 | L1258: =K1258/'Quellen & Annahmen'!$B$2 -> 0
A1259: 1258 | B1259: Var Energi | C1259: Energy | D1259: 0 | E1259: 0 | F1259: 0 | G1259: 0 | H1259: 0 | I1259: 0 | J1259: =SUM(E1259:I1259) -> 0 | K1259: =D1259+J1259 -> 0 | L1259: =K1259/'Quellen & Annahmen'!$B$2 -> 0
A1260: 1259 | B1260: Telus | C1260: Communication | D1260: 0 | E1260: 0 | F1260: 0 | G1260: 0 | H1260: 0 | I1260: 0 | J1260: =SUM(E1260:I1260) -> 0 | K1260: =D1260+J1260 -> 0 | L1260: =K1260/'Quellen & Annahmen'!$B$2 -> 0
A1261: 1260 | B1261: Sagax | C1261: Real Estate | D1261: 0 | E1261: 0 | F1261: 0 | G1261: 0 | H1261: 0 | I1261: 0 | J1261: =SUM(E1261:I1261) -> 0 | K1261: =D1261+J1261 -> 0 | L1261: =K1261/'Quellen & Annahmen'!$B$2 -> 0
A1262: 1261 | B1262: Contact Energy Ltd | C1262: Utilities | D1262: 0 | E1262: 0 | F1262: 0 | G1262: 0 | H1262: 0 | I1262: 0 | J1262: =SUM(E1262:I1262) -> 0 | K1262: =D1262+J1262 -> 0 | L1262: =K1262/'Quellen & Annahmen'!$B$2 -> 0
A1263: 1262 | B1263: Airtel Africa Plc | C1263: Communication | D1263: 0 | E1263: 0 | F1263: 0 | G1263: 0 | H1263: 0 | I1263: 0 | J1263: =SUM(E1263:I1263) -> 0 | K1263: =D1263+J1263 -> 0 | L1263: =K1263/'Quellen & Annahmen'!$B$2 -> 0
A1264: 1263 | B1264: Ivanhoe Mines Ltd | C1264: Materials | D1264: 0 | E1264: 0 | F1264: 0 | G1264: 0 | H1264: 0 | I1264: 0 | J1264: =SUM(E1264:I1264) -> 0 | K1264: =D1264+J1264 -> 0 | L1264: =K1264/'Quellen & Annahmen'!$B$2 -> 0
A1265: 1264 | B1265: Cts Eventim Ag | C1265: Communication | D1265: 0 | E1265: 0 | F1265: 0 | G1265: 0 | H1265: 0 | I1265: 0 | J1265: =SUM(E1265:I1265) -> 0 | K1265: =D1265+J1265 -> 0 | L1265: =K1265/'Quellen & Annahmen'!$B$2 -> 0
A1266: 1265 | B1266: Bc Vaud N | C1266: Financials | D1266: 0 | E1266: 0 | F1266: 0 | G1266: 0 | H1266: 0 | I1266: 0 | J1266: =SUM(E1266:I1266) -> 0 | K1266: =D1266+J1266 -> 0 | L1266: =K1266/'Quellen & Annahmen'!$B$2 -> 0
... A1289: 1288 | B1289: Hologic Inc | C1289: Health Care | D1289: 0 | E1289: 0 | F1289: 0 | G1289: 0 | H1289: 0 | I1289: 0 | J1289: =SUM(E1289:I1289) -> 0 | K1289: =D1289+J1289 -> 0 | L1289: =K1289/'Quellen & Annahmen'!$B$2 -> 0

Sheet Quellpositionen
A1: Quelle | B1: Holdings-Stichtag | C1: Ticker | D1: Wertpapiername Original | E1: Unternehmen konsolidiert | F1: Sektor | G1: Asset Class | H1: Gewicht im Instrument (%) | I1: Anteil am Depot (€) | J1: Offizielle Quelle
A2: Direktbestand | B2: 17.07.2026 | D2: AMD | E2: AMD | G2: Equity | H2: 100 | I2: 3896.55 | J2: Nutzerangaben im Chat
A3: Direktbestand | B3: 17.07.2026 | D3: Allianz | E3: Allianz | G3: Equity | H3: 100 | I3: 4210 | J3: Nutzerangaben im Chat
A4: Direktbestand | B4: 17.07.2026 | D4: Alphabet C (Google) | E4: Alphabet | G4: Equity | H4: 100 | I4: 3328.6 | J4: Nutzerangaben im Chat
A5: Direktbestand | B5: 17.07.2026 | D5: Apple | E5: Apple | G5: Equity | H5: 100 | I5: 1458.25 | J5: Nutzerangaben im Chat
A6: Direktbestand | B6: 17.07.2026 | D6: Berkshire Hathaway B | E6: Berkshire Hathaway | G6: Equity | H6: 100 | I6: 23600.5 | J6: Nutzerangaben im Chat
A7: Direktbestand | B7: 17.07.2026 | D7: Eli Lilly and Company | E7: Eli Lilly | G7: Equity | H7: 100 | I7: 2060.8 | J7: Nutzerangaben im Chat
A8: Direktbestand | B8: 17.07.2026 | D8: HSBC | E8: HSBC | G8: Equity | H8: 100 | I8: 1702.16 | J8: Nutzerangaben im Chat
A9: Direktbestand | B9: 17.07.2026 | D9: Linde | E9: Linde | G9: Equity | H9: 100 | I9: 896.8 | J9: Nutzerangaben im Chat
A10: Direktbestand | B10: 17.07.2026 | D10: Micron Technology | E10: Micron Technology | G10: Equity | H10: 100 | I10: 1492.2 | J10: Nutzerangaben im Chat
A11: Direktbestand | B11: 17.07.2026 | D11: Microsoft | E11: Microsoft | G11: Equity | H11: 100 | I11: 2410.1 | J11: Nutzerangaben im Chat
A12: Direktbestand | B12: 17.07.2026 | D12: Nvidia | E12: Nvidia | G12: Equity | H12: 100 | I12: 4430.5 | J12: Nutzerangaben im Chat
A13: Direktbestand | B13: 17.07.2026 | D13: Siemens | E13: Siemens | G13: Equity | H13: 100 | I13: 1851.5 | J13: Nutzerangaben im Chat
A14: Direktbestand | B14: 17.07.2026 | D14: TSMC Taiwan Semiconductor (ADR) | E14: TSMC | G14: Equity | H14: 100 | I14: 696 | J14: Nutzerangaben im Chat
A15: Global Titans 50 | B15: 16.07.2026 | C15: ABT | D15: ABBOTT LABORATORIES | E15: Abbott Laboratories | F15: Health Care | G15: Equity | H15: 0.51 | I15: 67.856316 | J15: https://www.ishares.com/ch/professionals/en/products/251769/ishares-dow-jones-global-titans-50-ucits-etf-de-fund
A16: Global Titans 50 | B16: 16.07.2026 | C16: ABBV | D16: ABBVIE INC | E16: Abbvie Inc | F16: Health Care | G16: Equity | H16: 1.32 | I16: 175.62811 | J16: https://www.ishares.com/ch/professionals/en/products/251769/ishares-dow-jones-global-titans-50-ucits-etf-de-fund
A17: Global Titans 50 | B17: 16.07.2026 | C17: ACN | D17: ACCENTURE PLC CLASS A | E17: Accenture Plc | F17: Information Technology | G17: Equity | H17: 0.26 | I17: 34.593416 | J17: https://www.ishares.com/ch/professionals/en/products/251769/ishares-dow-jones-global-titans-50-ucits-etf-de-fund
A18: Global Titans 50 | B18: 16.07.2026 | C18: GOOGL | D18: ALPHABET INC CLASS A | E18: Alphabet | F18: Communication | G18: Equity | H18: 4.27 | I18: 568.13033 | J18: https://www.ishares.com/ch/professionals/en/products/251769/ishares-dow-jones-global-titans-50-ucits-etf-de-fund
A19: Global Titans 50 | B19: 16.07.2026 | C19: GOOG | D19: ALPHABET INC CLASS C | E19: Alphabet | F19: Communication | G19: Equity | H19: 3.43 | I19: 456.36699 | J19: https://www.ishares.com/ch/professionals/en/products/251769/ishares-dow-jones-global-titans-50-ucits-etf-de-fund
A20: Global Titans 50 | B20: 16.07.2026 | C20: AMZN | D20: AMAZON.COM INC | E20: Amazon | F20: Consumer Discretionary | G20: Equity | H20: 7.21 | I20: 959.30204 | J20: https://www.ishares.com/ch/professionals/en/products/251769/ishares-dow-jones-global-titans-50-ucits-etf-de-fund
A21: Global Titans 50 | B21: 16.07.2026 | C21: AAPL | D21: APPLE INC | E21: Apple | F21: Information Technology | G21: Equity | H21: 8.82 | I21: 1173.5151 | J21: https://www.ishares.com/ch/professionals/en/products/251769/ishares-dow-jones-global-titans-50-ucits-etf-de-fund
A22: Global Titans 50 | B22: 16.07.2026 | C22: ASML | D22: ASML HOLDING NV | E22: ASML | F22: Information Technology | G22: Equity | H22: 2.09 | I22: 278.07784 | J22: https://www.ishares.com/ch/professionals/en/products/251769/ishares-dow-jones-global-titans-50-ucits-etf-de-fund
A23: Global Titans 50 | B23: 16.07.2026 | C23: AZN | D23: ASTRAZENECA PLC | E23: Astrazeneca Plc | F23: Health Care | G23: Equity | H23: 0.78 | I23: 103.78025 | J23: https://www.ishares.com/ch/professionals/en/products/251769/ishares-dow-jones-global-titans-50-ucits-etf-de-fund
A24: Global Titans 50 | B24: 16.07.2026 | C24: AVGO | D24: BROADCOM INC | E24: Broadcom | F24: Information Technology | G24: Equity | H24: 5.22 | I24: 694.52935 | J24: https://www.ishares.com/ch/professionals/en/products/251769/ishares-dow-jones-global-titans-50-ucits-etf-de-fund
A25: Global Titans 50 | B25: 16.07.2026 | C25: CAT | D25: CATERPILLAR INC | E25: Caterpillar | F25: Industrials | G25: Equity | H25: 1.19 | I25: 158.3314 | J25: https://www.ishares.com/ch/professionals/en/products/251769/ishares-dow-jones-global-titans-50-ucits-etf-de-fund
A26: Global Titans 50 | B26: 16.07.2026 | C26: CVX | D26: CHEVRON CORP | E26: Chevron Corp | F26: Energy | G26: Equity | H26: 1.01 | I26: 134.38212 | J26: https://www.ishares.com/ch/professionals/en/products/251769/ishares-dow-jones-global-titans-50-ucits-etf-de-fund
... A1749: World Value | B1749: 16.07.2026 | C1749: ZM | D1749: ZOOM COMMUNICATIONS INC CLASS A | E1749: Zoom Communications Inc | F1749: Information Technology | G1749: Equity | H1749: 0.22 | I1749: 2.510288 | J1749: https://www.ishares.com/ch/individual/en/products/270048/ishares-msci-world-value-factor-ucits-etf
A1750: boerse.de-Aktienfonds | B1750: 10.07.2026 | D1750: AMD | E1750: AMD | G1750: Equity | H1750: 2.5439597 | I1750: 573.30194 | J1750: https://www.boerse-aktienfonds.de/
A1751: boerse.de-Aktienfonds | B1751: 10.07.2026 | D1751: ASML | E1751: ASML | G1751: Equity | H1751: 2.4327025 | I1751: 548.22921 | J1751: https://www.boerse-aktienfonds.de/
A1752: boerse.de-Aktienfonds | B1752: 10.07.2026 | D1752: Allianz | E1752: Allianz | G1752: Equity | H1752: 2.5439319 | I1752: 573.29566 | J1752: https://www.boerse-aktienfonds.de/
A1753: boerse.de-Aktienfonds | B1753: 10.07.2026 | D1753: Alphabet | E1753: Alphabet | G1753: Equity | H1753: 2.4631112 | I1753: 555.08205 | J1753: https://www.boerse-aktienfonds.de/
A1754: boerse.de-Aktienfonds | B1754: 10.07.2026 | D1754: Amazon | E1754: Amazon | G1754: Equity | H1754: 2.5197583 | I1754: 567.84793 | J1754: https://www.boerse-aktienfonds.de/
A1755: boerse.de-Aktienfonds | B1755: 10.07.2026 | D1755: Amphenol | E1755: Amphenol | G1755: Equity | H1755: 2.3590347 | I1755: 531.62759 | J1755: https://www.boerse-aktienfonds.de/
A1756: boerse.de-Aktienfonds | B1756: 10.07.2026 | D1756: Apple | E1756: Apple | G1756: Equity | H1756: 2.7295429 | I1756: 615.1246 | J1756: https://www.boerse-aktienfonds.de/
A1757: boerse.de-Aktienfonds | B1757: 10.07.2026 | D1757: AutoZone | E1757: Autozone | G1757: Equity | H1757: 2.4027193 | I1757: 541.47225 | J1757: https://www.boerse-aktienfonds.de/
A1758: boerse.de-Aktienfonds | B1758: 10.07.2026 | D1758: Berkshire Hathaway | E1758: Berkshire Hathaway | G1758: Equity | H1758: 2.4537752 | I1758: 552.97811 | J1758: https://www.boerse-aktienfonds.de/
A1759: boerse.de-Aktienfonds | B1759: 10.07.2026 | D1759: BlackRock | E1759: BlackRock | G1759: Equity | H1759: 2.6567487 | I1759: 598.71983 | J1759: https://www.boerse-aktienfonds.de/
A1760: boerse.de-Aktienfonds | B1760: 10.07.2026 | D1760: Booking Holdings | E1760: Booking Holdings | G1760: Equity | H1760: 2.4103647 | I1760: 543.19522 | J1760: https://www.boerse-aktienfonds.de/
A1761: boerse.de-Aktienfonds | B1761: 10.07.2026 | D1761: Caterpillar | E1761: Caterpillar | G1761: Equity | H1761: 2.2826275 | I1761: 514.4086 | J1761: https://www.boerse-aktienfonds.de/
... A1823: boerse.de-Technologiefonds – Basisportfolio | B1823: 16.07.2026 | D1823: Texas Instruments | E1823: Texas Instruments | G1823: Equity | H1823: 1.729718 | I1823: 81.886234 | J1823: https://www.boerse-technologiefonds.de/

Sheet Direktbestand
A1: Unternehmen konsolidiert | B1: Wertpapier | C1: WKN | D1: ISIN | E1: Stückzahl | F1: Kurs (€) | G1: Aktueller Wert (€) | H1: Stand
A2: Berkshire Hathaway | B2: Berkshire Hathaway B | C2: A0YJQ2 | D2: US0846707026 | E2: 55 | F2: 429.1 | G2: 23600.5 | H2: 17.07.2026
A3: Allianz | B3: Allianz | C3: 840400 | D3: DE0008404005 | E3: 10 | F3: 421 | G3: 4210 | H3: 17.07.2026
A4: Nvidia | B4: Nvidia | C4: 918422 | D4: US67066G1040 | E4: 25 | F4: 177.22 | G4: 4430.5 | H4: 17.07.2026
A5: AMD | B5: AMD | C5: 863186 | D5: US0079031078 | E5: 9 | F5: 432.95 | G5: 3896.55 | H5: 17.07.2026
A6: Alphabet | B6: Alphabet C (Google) | C6: A14Y6H | D6: US02079K1079 | E6: 11 | F6: 302.6 | G6: 3328.6 | H6: 17.07.2026
A7: Micron Technology | B7: Micron Technology | C7: 869020 | D7: US5951121038 | E7: 2 | F7: 746.1 | G7: 1492.2 | H7: 17.07.2026
A8: Microsoft | B8: Microsoft | C8: 870747 | D8: US5949181045 | E8: 7 | F8: 344.3 | G8: 2410.1 | H8: 17.07.2026
A9: Eli Lilly | B9: Eli Lilly and Company | C9: 858560 | D9: US5324571083 | E9: 2 | F9: 1030.4 | G9: 2060.8 | H9: 17.07.2026
A10: Siemens | B10: Siemens | C10: 723610 | D10: DE0007236101 | E10: 7 | F10: 264.5 | G10: 1851.5 | H10: 17.07.2026
A11: HSBC | B11: HSBC | C11: 923893 | D11: GB0005405286 | E11: 97 | F11: 17.55 | G11: 1702.16 | H11: 17.07.2026
A12: Apple | B12: Apple | C12: 865985 | D12: US0378331005 | E12: 5 | F12: 291.65 | G12: 1458.25 | H12: 17.07.2026
A13: Linde | B13: Linde | C13: A3D7VW | D13: IE000S9YS762 | E13: 2 | F13: 448.4 | G13: 896.8 | H13: 17.07.2026
A14: TSMC | B14: TSMC Taiwan Semiconductor (ADR) | C14: 909800 | D14: US8740391003 | E14: 2 | F14: 348 | G14: 696 | H14: 17.07.2026

Sheet Quellen & Annahmen
A1: Quellen, Annahmen und Auflösungsgrad
A2: Gesamtvermögen (€) | B2: 110400.89
A4: Instrument | B4: Depotwert (€) | C4: Depotstand | D4: Holdings-Stichtag | E4: Öffentlich auflösbarer Anteil | F4: Aufgelöster Betrag (€) | G4: Nicht aufgelöst / Nicht-Aktien (€) | H4: Methode / Hinweis | I4: Offizielle Quelle
A5: Direktbestand | B5: 52033.96 | C5: 17.07.2026 | D5: 17.07.2026 | E5: 1 | F5: 52033.96 | G5: 0 | H5: Direkte Nutzerangaben; vollständig berücksichtigt. | I5: Nutzerangaben im Chat
A6: boerse.de-Aktienfonds | B6: 22535.81 | C6: 17.07.2026 | D6: 10.07.2026 | E6: 1 | F6: 22535.81 | G6: 0 | H6: 40 veröffentlichte Aktien nach ihren Marktwerten gewichtet und auf das Aktienportfolio normiert. | I6: https://www.boerse-aktienfonds.de/
A7: Global Titans 50 | B7: 13305.16 | C7: 17.07.2026 | D7: 16.07.2026 | E7: 0.9975 | F7: 13271.897 | G7: 33.2629 | H7: Alle in der offiziellen iShares-Datei als Equity klassifizierten Positionen. | I7: https://www.ishares.com/ch/professionals/en/products/251769/ishares-dow-jones-global-titans-50-ucits-etf-de-fund
A8: boerse.de-Technologiefonds | B8: 4734.08 | C8: 17.07.2026 | D8: 16.07.2026 | E8: 0.6 | F8: 2840.448 | G8: 1893.632 | H8: Nur das vollständig veröffentlichte 60%-Basisportfolio. Das 40%-Darwin-Portfolio (>500 Aktien) ist nicht vollständig öffentlich auflösbar. | I8: https://www.boerse-technologiefonds.de/
A9: MSCI World | B9: 3363.12 | C9: 17.07.2026 | D9: 16.07.2026 | E9: 0.9982 | F9: 3357.0664 | G9: 6.053616 | H9: Alle in der offiziellen iShares-Datei als Equity klassifizierten Positionen. | I9: https://www.ishares.com/ch/individual/en/products/251882/ishares-msci-world-ucits-etf-acc-fund
A10: World Value | B10: 1141.04 | C10: 17.07.2026 | D10: 16.07.2026 | E10: 0.9949 | F10: 1135.2207 | G10: 5.819304 | H10: Alle in der offiziellen iShares-Datei als Equity klassifizierten Positionen. | I10: https://www.ishares.com/ch/individual/en/products/270048/ishares-msci-world-value-factor-ucits-etf
A11: Xetra Gold | B11: 6988.64 | C11: 17.07.2026 | D11: - | E11: 0 | F11: 0 | G11: 6988.64 | H11: Gold-ETC; keine Einzelaktien. | I11: Nutzerangaben im Chat
A12: WisdomTree Physical Bitcoin | B12: 799.08 | C12: 17.07.2026 | D12: - | E12: 0 | F12: 0 | G12: 799.08 | H12: Bitcoin-ETP; keine Einzelaktien. | I12: Nutzerangaben im Chat
A13: Bargeld | B13: 5500 | C13: 17.07.2026 | D13: - | E13: 0 | F13: 0 | G13: 5500 | H13: Bargeld; keine Einzelaktien. | I13: Nutzerangaben im Chat
A15: Kontrollsumme Gesamtvermögen | B15: =SUM(B5:B13) -> 110400.89 | F15: =SUM(F5:F13) -> 95174.402 | G15: =SUM(G5:G13) -> 15226.488
